trame/__init__.py
trame/modules/__init__.py
trame/modules/leaflet.py
trame/modules/leaflet2.py
trame/modules/leaflet3.py
trame/widgets/__init__.py
trame/widgets/leaflet.py
trame/widgets/leaflet2.py
trame/widgets/leaflet3.py
trame_leaflet/LICENSE
trame_leaflet/__init__.py
trame_leaflet/module/__init__.py
trame_leaflet/module/leaflet2/__init__.py
trame_leaflet/module/leaflet2/serve/demo.html
trame_leaflet/module/leaflet2/serve/trame-leaflet.common.js
trame_leaflet/module/leaflet2/serve/trame-leaflet.common.js.map
trame_leaflet/module/leaflet2/serve/trame-leaflet.css
trame_leaflet/module/leaflet2/serve/trame-leaflet.umd.js
trame_leaflet/module/leaflet2/serve/trame-leaflet.umd.js.map
trame_leaflet/module/leaflet2/serve/trame-leaflet.umd.min.js
trame_leaflet/module/leaflet2/serve/trame-leaflet.umd.min.js.map
trame_leaflet/module/leaflet2/serve/tramelayers-2x.png
trame_leaflet/module/leaflet2/serve/tramelayers.png
trame_leaflet/module/leaflet2/serve/tramemarker-icon-2x.png
trame_leaflet/module/leaflet2/serve/tramemarker-icon.png
trame_leaflet/module/leaflet2/serve/tramemarker-shadow.png
trame_leaflet/module/leaflet3/__init__.py
trame_leaflet/module/leaflet3/vue3.py
trame_leaflet/module/leaflet3/vue3/style.css
trame_leaflet/module/leaflet3/vue3/trame-leaflet3.umd.js
trame_leaflet/widgets/__init__.py
trame_leaflet/widgets/leaflet.py
trame_leaflet/widgets/leaflet3.py
trame_leaflet-1.2.4.dist-info/LICENSE
trame_leaflet-1.2.4.dist-info/METADATA
trame_leaflet-1.2.4.dist-info/WHEEL
trame_leaflet-1.2.4.dist-info/top_level.txt
trame_leaflet-1.2.4.dist-info/RECORD
